setup.py
ConeXi.egg-info/PKG-INFO
ConeXi.egg-info/SOURCES.txt
ConeXi.egg-info/dependency_links.txt
ConeXi.egg-info/top_level.txt
combineranks/ConeXi.py