Metadata-Version: 2.1
Name: ConeXi
Version: 1.0
Summary: Combining Explanations and Interpretations - ConeXi.
Author: José de Sousa Ribeiro Filho
Author-email: jose.sousa.filho@gmail.com
